AUTHORS
MANIFEST.in
README.rst
setup.py
django_like_button.egg-info/PKG-INFO
django_like_button.egg-info/SOURCES.txt
django_like_button.egg-info/dependency_links.txt
django_like_button.egg-info/top_level.txt
like_button/__init__.py
like_button/models.py
like_button/urls.py
like_button/views.py
like_button/templates/channel.html
like_button/templates/like_button/like_button_js_tag.html
like_button/templates/like_button/like_button_tag.html
like_button/templatetags/__init__.py
like_button/templatetags/like_button.py