Metadata-Version: 1.0
Name: django-like-button
Version: 0.0.7
Summary: Django App for adding a Facebook like button
Home-page: https://github.com/johncosta/django-like-button
Author: John Costa
Author-email: john.costa@gmil.com
License: UNKNOWN
Platform: UNKNOWN
Classifier: Programming Language :: Python
Classifier: Framework :: Django
Classifier: Intended Audience :: Developers
Classifier: Operating System :: OS Independent
Classifier: Topic :: Software Development :: Libraries :: Python Modules
Classifier: Topic :: Utilities
